girder_ninjato_api/__init__.py
girder_ninjato_api/async_job_utils.py
girder_ninjato_api/endpoint_utils.py
girder_ninjato_api/utils.py
girder_ninjato_api/web_client/main.js
girder_ninjato_api/web_client/package.json
girder_ninjato_api-0.1.0.dist-info/LICENSE
girder_ninjato_api-0.1.0.dist-info/METADATA
girder_ninjato_api-0.1.0.dist-info/WHEEL
girder_ninjato_api-0.1.0.dist-info/entry_points.txt
girder_ninjato_api-0.1.0.dist-info/top_level.txt
girder_ninjato_api-0.1.0.dist-info/RECORD
