Metadata-Version: 2.1
Name: girder-ninjato-api
Version: 0.1.0
Summary: Girder Ninjato API plugin
Home-page: https://github.com/RENCI/ninjato/tree/main/girder/plugins/ninjato_api
Author: Hong Yi
Author-email: hongyi@renci.org
License: Apache Software License 2.0
Keywords: girder-plugin,ninjato_api
Classifier: Development Status :: 2 - Pre-Alpha
Classifier: License :: OSI Approved :: Apache Software License
Classifier: Natural Language :: English
Classifier: Programming Language :: Python :: 3
Classifier: Programming Language :: Python :: 3.6
Classifier: Programming Language :: Python :: 3.7
Classifier: Programming Language :: Python :: 3.8
License-File: LICENSE
Requires-Dist: girder (>=3.0.0a1)
